skillgraph/__init__.py
skillgraph-0.0.1.dist-info/METADATA
skillgraph-0.0.1.dist-info/WHEEL
skillgraph-0.0.1.dist-info/top_level.txt
skillgraph-0.0.1.dist-info/RECORD
